{"link": [42708, 2945], "path": "null", "label": [["PT0"], ["IT0"], 0], "type": ["SUBJECT_PROCESS", "EVENT_CLOSE", "IPC_OBJECT_PIPE_UNNAMED"], "initlink": [22158, 0]}
{"link": [42708, 2945], "path": "null", "label": [["PT0"], ["IT0"], 0], "type": ["SUBJECT_PROCESS", "EVENT_CLOSE", "IPC_OBJECT_PIPE_UNNAMED"], "initlink": [22158, 0]}
{"link": [42708, 42709], "path": "null", "label": [["PT0"], ["PT0"], 0], "type": ["SUBJECT_PROCESS", "EVENT_FORK", "SUBJECT_PROCESS"], "initlink": [22158, 22159]}
{"link": [42708, 2946], "path": "null", "label": [["PT0"], ["IT0"], 0], "type": ["SUBJECT_PROCESS", "EVENT_CLOSE", "IPC_OBJECT_PIPE_UNNAMED"], "initlink": [22158, 0]}
{"link": [42708, 42710], "path": "null", "label": [["PT0"], ["PT0"], 0], "type": ["SUBJECT_PROCESS", "EVENT_FORK", "SUBJECT_PROCESS"], "initlink": [22158, 22160]}
{"link": [42708, 2946], "path": "null", "label": [["PT0"], ["IT0"], 0], "type": ["SUBJECT_PROCESS", "EVENT_CLOSE", "IPC_OBJECT_PIPE_UNNAMED"], "initlink": [22158, 0]}
{"link": [42708, 2947], "path": "null", "label": [["PT0"], ["IT0"], 0], "type": ["SUBJECT_PROCESS", "EVENT_CLOSE", "IPC_OBJECT_PIPE_UNNAMED"], "initlink": [22158, 0]}
{"link": [42708, 42711], "path": "null", "label": [["PT0"], ["PT0"], 0], "type": ["SUBJECT_PROCESS", "EVENT_FORK", "SUBJECT_PROCESS"], "initlink": [22158, 22161]}
{"link": [42708, 2947], "path": "null", "label": [["PT0"], ["IT0"], 0], "type": ["SUBJECT_PROCESS", "EVENT_CLOSE", "IPC_OBJECT_PIPE_UNNAMED"], "initlink": [22158, 0]}
