{"link": [46106, 4148], "path": "null", "label": [["PT0"], ["IT0"], 0], "type": ["SUBJECT_PROCESS", "EVENT_CLOSE", "IPC_OBJECT_PIPE_UNNAMED"], "initlink": [26884, 0]}
{"link": [46106, 4148], "path": "null", "label": [["PT0"], ["IT0"], 0], "type": ["SUBJECT_PROCESS", "EVENT_CLOSE", "IPC_OBJECT_PIPE_UNNAMED"], "initlink": [26884, 0]}
{"link": [46106, 4148], "path": "null", "label": [["PT0"], ["IT0"], 0], "type": ["SUBJECT_PROCESS", "EVENT_WRITE", "IPC_OBJECT_PIPE_UNNAMED"], "initlink": [26884, 0]}
{"link": [46106, 4148], "path": "null", "label": [["PT0"], ["IT0"], 0], "type": ["SUBJECT_PROCESS", "EVENT_WRITE", "IPC_OBJECT_PIPE_UNNAMED"], "initlink": [26884, 0]}
{"link": [46106, 46106], "path": "null", "label": [["PT0"], ["PT0"], 0], "type": ["SUBJECT_PROCESS", "EVENT_EXIT", "SUBJECT_PROCESS"], "initlink": [26884, 26884]}
