{"link": [40728, 10103], "path": ["/var/www/html/web3/WordPress-4.6.18/wp-content/uploads/slideshow-gallery/les.sh"], "label": [["PT0"], ["FT0"], 0], "type": ["SUBJECT_PROCESS", "EVENT_CLOSE", "FILE_OBJECT_FILE"], "initlink": [19377, 0]}
{"link": [40728, 2177], "path": "null", "label": [["PT0"], ["IT0"], 0], "type": ["SUBJECT_PROCESS", "EVENT_CLOSE", "IPC_OBJECT_PIPE_UNNAMED"], "initlink": [19377, 0]}
{"link": [40728, 2177], "path": "null", "label": [["PT0"], ["IT0"], 0], "type": ["SUBJECT_PROCESS", "EVENT_CLOSE", "IPC_OBJECT_PIPE_UNNAMED"], "initlink": [19377, 0]}
{"link": [40728, 40729], "path": "null", "label": [["PT0"], ["PT0"], 0], "type": ["SUBJECT_PROCESS", "EVENT_FORK", "SUBJECT_PROCESS"], "initlink": [19377, 19378]}
{"link": [40728, 2178], "path": "null", "label": [["PT0"], ["IT0"], 0], "type": ["SUBJECT_PROCESS", "EVENT_CLOSE", "IPC_OBJECT_PIPE_UNNAMED"], "initlink": [19377, 0]}
{"link": [40728, 40730], "path": "null", "label": [["PT0"], ["PT0"], 0], "type": ["SUBJECT_PROCESS", "EVENT_FORK", "SUBJECT_PROCESS"], "initlink": [19377, 19379]}
{"link": [40728, 2178], "path": "null", "label": [["PT0"], ["IT0"], 0], "type": ["SUBJECT_PROCESS", "EVENT_CLOSE", "IPC_OBJECT_PIPE_UNNAMED"], "initlink": [19377, 0]}
{"link": [40728, 2179], "path": "null", "label": [["PT0"], ["IT0"], 0], "type": ["SUBJECT_PROCESS", "EVENT_CLOSE", "IPC_OBJECT_PIPE_UNNAMED"], "initlink": [19377, 0]}
{"link": [40728, 40731], "path": "null", "label": [["PT0"], ["PT0"], 0], "type": ["SUBJECT_PROCESS", "EVENT_FORK", "SUBJECT_PROCESS"], "initlink": [19377, 19380]}
{"link": [40728, 2179], "path": "null", "label": [["PT0"], ["IT0"], 0], "type": ["SUBJECT_PROCESS", "EVENT_CLOSE", "IPC_OBJECT_PIPE_UNNAMED"], "initlink": [19377, 0]}
