{"link": [46306, 4240], "path": "null", "label": [["PT0"], ["IT0"], 0], "type": ["SUBJECT_PROCESS", "EVENT_CLOSE", "IPC_OBJECT_PIPE_UNNAMED"], "initlink": [27123, 0]}
{"link": [46306, 4240], "path": "null", "label": [["PT0"], ["IT0"], 0], "type": ["SUBJECT_PROCESS", "EVENT_CLOSE", "IPC_OBJECT_PIPE_UNNAMED"], "initlink": [27123, 0]}
{"link": [46306, 46307], "path": "null", "label": [["PT0"], ["PT0"], 0], "type": ["SUBJECT_PROCESS", "EVENT_FORK", "SUBJECT_PROCESS"], "initlink": [27123, 27124]}
{"link": [46306, 4241], "path": "null", "label": [["PT0"], ["IT0"], 0], "type": ["SUBJECT_PROCESS", "EVENT_CLOSE", "IPC_OBJECT_PIPE_UNNAMED"], "initlink": [27123, 0]}
{"link": [46306, 46308], "path": "null", "label": [["PT0"], ["PT0"], 0], "type": ["SUBJECT_PROCESS", "EVENT_FORK", "SUBJECT_PROCESS"], "initlink": [27123, 27125]}
{"link": [46306, 4241], "path": "null", "label": [["PT0"], ["IT0"], 0], "type": ["SUBJECT_PROCESS", "EVENT_CLOSE", "IPC_OBJECT_PIPE_UNNAMED"], "initlink": [27123, 0]}
{"link": [46306, 4242], "path": "null", "label": [["PT0"], ["IT0"], 0], "type": ["SUBJECT_PROCESS", "EVENT_CLOSE", "IPC_OBJECT_PIPE_UNNAMED"], "initlink": [27123, 0]}
{"link": [46306, 46309], "path": "null", "label": [["PT0"], ["PT0"], 0], "type": ["SUBJECT_PROCESS", "EVENT_FORK", "SUBJECT_PROCESS"], "initlink": [27123, 27126]}
{"link": [46306, 4242], "path": "null", "label": [["PT0"], ["IT0"], 0], "type": ["SUBJECT_PROCESS", "EVENT_CLOSE", "IPC_OBJECT_PIPE_UNNAMED"], "initlink": [27123, 0]}
