{"link": [47220, 47219], "path": "null", "label": [["PT0"], ["PT0"], 0], "type": ["SUBJECT_PROCESS", "EVENT_FORK", "SUBJECT_PROCESS"], "initlink": [28454, 28455]}
{"link": [47220, 47221], "path": "null", "label": [["PT0"], ["PT97"], 0], "type": ["SUBJECT_PROCESS", "EVENT_FORK", "SUBJECT_PROCESS"], "initlink": [28454, 28456]}
{"link": [47220, 4565], "path": "null", "label": [["PT0"], ["IT0"], 0], "type": ["SUBJECT_PROCESS", "EVENT_CLOSE", "IPC_OBJECT_PIPE_UNNAMED"], "initlink": [28454, 0]}
{"link": [47220, 47222], "path": "null", "label": [["PT0"], ["PT0"], 0], "type": ["SUBJECT_PROCESS", "EVENT_FORK", "SUBJECT_PROCESS"], "initlink": [28454, 28457]}
{"link": [47220, 4565], "path": "null", "label": [["PT0"], ["IT0"], 0], "type": ["SUBJECT_PROCESS", "EVENT_CLOSE", "IPC_OBJECT_PIPE_UNNAMED"], "initlink": [28454, 0]}
