{"link": [50526, 5637], "path": "null", "label": [["PT97"], ["IT0"], 0], "type": ["SUBJECT_PROCESS", "EVENT_CLOSE", "IPC_OBJECT_PIPE_UNNAMED"], "initlink": [33052, 0]}
{"link": [50526, 5636], "path": "null", "label": [["PT97"], ["IT0"], 0], "type": ["SUBJECT_PROCESS", "EVENT_CLOSE", "IPC_OBJECT_PIPE_UNNAMED"], "initlink": [33052, 0]}
{"link": [50526, 5637], "path": "null", "label": [["PT97"], ["IT0"], 0], "type": ["SUBJECT_PROCESS", "EVENT_CLOSE", "IPC_OBJECT_PIPE_UNNAMED"], "initlink": [33052, 0]}
{"link": [50526, 50526], "path": "null", "label": [["PT97"], ["PT97"], 0], "type": ["SUBJECT_PROCESS", "EVENT_EXECUTE", "SUBJECT_PROCESS"], "initlink": [33052, 33052]}
