{"link": [50875, 10103], "path": ["/var/www/html/web3/WordPress-4.6.18/wp-content/uploads/slideshow-gallery/les.sh"], "label": [["PT0"], ["FT0"], 1], "type": ["SUBJECT_PROCESS", "EVENT_CLOSE", "FILE_OBJECT_FILE"], "initlink": [33713, 0]}
{"link": [50875, 5731], "path": "null", "label": [["PT0"], ["IT0"], 1], "type": ["SUBJECT_PROCESS", "EVENT_CLOSE", "IPC_OBJECT_PIPE_UNNAMED"], "initlink": [33713, 0]}
{"link": [50875, 5731], "path": "null", "label": [["PT0"], ["IT0"], 1], "type": ["SUBJECT_PROCESS", "EVENT_CLOSE", "IPC_OBJECT_PIPE_UNNAMED"], "initlink": [33713, 0]}
{"link": [50875, 50876], "path": "null", "label": [["PT0"], ["PT0"], 1], "type": ["SUBJECT_PROCESS", "EVENT_FORK", "SUBJECT_PROCESS"], "initlink": [33713, 33714]}
{"link": [50875, 5732], "path": "null", "label": [["PT0"], ["IT0"], 1], "type": ["SUBJECT_PROCESS", "EVENT_CLOSE", "IPC_OBJECT_PIPE_UNNAMED"], "initlink": [33713, 0]}
{"link": [50875, 50877], "path": "null", "label": [["PT0"], ["PT0"], 1], "type": ["SUBJECT_PROCESS", "EVENT_FORK", "SUBJECT_PROCESS"], "initlink": [33713, 33715]}
{"link": [50875, 5732], "path": "null", "label": [["PT0"], ["IT0"], 1], "type": ["SUBJECT_PROCESS", "EVENT_CLOSE", "IPC_OBJECT_PIPE_UNNAMED"], "initlink": [33713, 0]}
{"link": [50875, 5733], "path": "null", "label": [["PT0"], ["IT0"], 1], "type": ["SUBJECT_PROCESS", "EVENT_CLOSE", "IPC_OBJECT_PIPE_UNNAMED"], "initlink": [33713, 0]}
{"link": [50875, 50878], "path": "null", "label": [["PT0"], ["PT0"], 1], "type": ["SUBJECT_PROCESS", "EVENT_FORK", "SUBJECT_PROCESS"], "initlink": [33713, 33716]}
{"link": [50875, 5733], "path": "null", "label": [["PT0"], ["IT0"], 1], "type": ["SUBJECT_PROCESS", "EVENT_CLOSE", "IPC_OBJECT_PIPE_UNNAMED"], "initlink": [33713, 0]}
