{"link": [34974, 34973], "path": "null", "label": [["PT0"], ["PT0"], 0], "type": ["SUBJECT_PROCESS", "EVENT_FORK", "SUBJECT_PROCESS"], "initlink": [9005, 9006]}
{"link": [34974, 182], "path": "null", "label": [["PT0"], ["IT0"], 0], "type": ["SUBJECT_PROCESS", "EVENT_CLOSE", "IPC_OBJECT_PIPE_UNNAMED"], "initlink": [9005, 0]}
{"link": [34974, 34975], "path": "null", "label": [["PT0"], ["PT0"], 0], "type": ["SUBJECT_PROCESS", "EVENT_FORK", "SUBJECT_PROCESS"], "initlink": [9005, 9007]}
{"link": [34974, 182], "path": "null", "label": [["PT0"], ["IT0"], 0], "type": ["SUBJECT_PROCESS", "EVENT_CLOSE", "IPC_OBJECT_PIPE_UNNAMED"], "initlink": [9005, 0]}
{"link": [34974, 183], "path": "null", "label": [["PT0"], ["IT0"], 0], "type": ["SUBJECT_PROCESS", "EVENT_CLOSE", "IPC_OBJECT_PIPE_UNNAMED"], "initlink": [9005, 0]}
{"link": [34974, 34976], "path": "null", "label": [["PT0"], ["PT0"], 0], "type": ["SUBJECT_PROCESS", "EVENT_FORK", "SUBJECT_PROCESS"], "initlink": [9005, 9008]}
{"link": [34974, 183], "path": "null", "label": [["PT0"], ["IT0"], 0], "type": ["SUBJECT_PROCESS", "EVENT_CLOSE", "IPC_OBJECT_PIPE_UNNAMED"], "initlink": [9005, 0]}
{"link": [34974, 184], "path": "null", "label": [["PT0"], ["IT0"], 0], "type": ["SUBJECT_PROCESS", "EVENT_CLOSE", "IPC_OBJECT_PIPE_UNNAMED"], "initlink": [9005, 0]}
{"link": [34974, 34977], "path": "null", "label": [["PT0"], ["PT0"], 0], "type": ["SUBJECT_PROCESS", "EVENT_FORK", "SUBJECT_PROCESS"], "initlink": [9005, 9009]}
{"link": [34974, 184], "path": "null", "label": [["PT0"], ["IT0"], 0], "type": ["SUBJECT_PROCESS", "EVENT_CLOSE", "IPC_OBJECT_PIPE_UNNAMED"], "initlink": [9005, 0]}
