{"link": [47341, 10103], "path": ["/var/www/html/web3/WordPress-4.6.18/wp-content/uploads/slideshow-gallery/les.sh"], "label": [["PT97"], ["FT0"], 0], "type": ["SUBJECT_PROCESS", "EVENT_CLOSE", "FILE_OBJECT_FILE"], "initlink": [28647, 0]}
{"link": [47341, 4603], "path": "null", "label": [["PT97"], ["IT0"], 0], "type": ["SUBJECT_PROCESS", "EVENT_CLOSE", "IPC_OBJECT_PIPE_UNNAMED"], "initlink": [28647, 0]}
{"link": [47341, 4603], "path": "null", "label": [["PT97"], ["IT0"], 0], "type": ["SUBJECT_PROCESS", "EVENT_CLOSE", "IPC_OBJECT_PIPE_UNNAMED"], "initlink": [28647, 0]}
{"link": [47341, 47342], "path": "null", "label": [["PT97"], ["PT97"], 0], "type": ["SUBJECT_PROCESS", "EVENT_FORK", "SUBJECT_PROCESS"], "initlink": [28647, 28648]}
{"link": [47341, 4604], "path": "null", "label": [["PT97"], ["IT0"], 0], "type": ["SUBJECT_PROCESS", "EVENT_CLOSE", "IPC_OBJECT_PIPE_UNNAMED"], "initlink": [28647, 0]}
{"link": [47341, 47343], "path": "null", "label": [["PT97"], ["PT0"], 0], "type": ["SUBJECT_PROCESS", "EVENT_FORK", "SUBJECT_PROCESS"], "initlink": [28647, 28649]}
{"link": [47341, 4604], "path": "null", "label": [["PT97"], ["IT0"], 0], "type": ["SUBJECT_PROCESS", "EVENT_CLOSE", "IPC_OBJECT_PIPE_UNNAMED"], "initlink": [28647, 0]}
{"link": [47341, 4605], "path": "null", "label": [["PT97"], ["IT0"], 0], "type": ["SUBJECT_PROCESS", "EVENT_CLOSE", "IPC_OBJECT_PIPE_UNNAMED"], "initlink": [28647, 0]}
{"link": [47341, 47344], "path": "null", "label": [["PT97"], ["PT0"], 0], "type": ["SUBJECT_PROCESS", "EVENT_FORK", "SUBJECT_PROCESS"], "initlink": [28647, 28650]}
{"link": [47341, 4605], "path": "null", "label": [["PT97"], ["IT0"], 0], "type": ["SUBJECT_PROCESS", "EVENT_CLOSE", "IPC_OBJECT_PIPE_UNNAMED"], "initlink": [28647, 0]}
{"link": [47341, 4606], "path": "null", "label": [["PT97"], ["IT0"], 0], "type": ["SUBJECT_PROCESS", "EVENT_CLOSE", "IPC_OBJECT_PIPE_UNNAMED"], "initlink": [28647, 0]}
{"link": [47341, 47345], "path": "null", "label": [["PT97"], ["PT0"], 0], "type": ["SUBJECT_PROCESS", "EVENT_FORK", "SUBJECT_PROCESS"], "initlink": [28647, 28651]}
{"link": [47341, 4606], "path": "null", "label": [["PT97"], ["IT0"], 0], "type": ["SUBJECT_PROCESS", "EVENT_CLOSE", "IPC_OBJECT_PIPE_UNNAMED"], "initlink": [28647, 0]}
