{"link": [51899, 6066], "path": "null", "label": [["PT97"], ["IT0"], 0], "type": ["SUBJECT_PROCESS", "EVENT_CLOSE", "IPC_OBJECT_PIPE_UNNAMED"], "initlink": [35487, 0]}
{"link": [51899, 6066], "path": "null", "label": [["PT97"], ["IT0"], 0], "type": ["SUBJECT_PROCESS", "EVENT_CLOSE", "IPC_OBJECT_PIPE_UNNAMED"], "initlink": [35487, 0]}
{"link": [51899, 6066], "path": "null", "label": [["PT97"], ["IT0"], 0], "type": ["SUBJECT_PROCESS", "EVENT_WRITE", "IPC_OBJECT_PIPE_UNNAMED"], "initlink": [35487, 0]}
{"link": [51899, 6066], "path": "null", "label": [["PT97"], ["IT0"], 0], "type": ["SUBJECT_PROCESS", "EVENT_WRITE", "IPC_OBJECT_PIPE_UNNAMED"], "initlink": [35487, 0]}
{"link": [51899, 51899], "path": "null", "label": [["PT97"], ["PT97"], 0], "type": ["SUBJECT_PROCESS", "EVENT_EXIT", "SUBJECT_PROCESS"], "initlink": [35487, 35487]}
