{"link": [52405, 6300], "path": "null", "label": [["PT0"], ["IT0"], 0], "type": ["SUBJECT_PROCESS", "EVENT_CLOSE", "IPC_OBJECT_PIPE_UNNAMED"], "initlink": [36187, 0]}
{"link": [52405, 6300], "path": "null", "label": [["PT0"], ["IT0"], 0], "type": ["SUBJECT_PROCESS", "EVENT_READ", "IPC_OBJECT_PIPE_UNNAMED"], "initlink": [36187, 0]}
{"link": [52405, 6300], "path": "null", "label": [["PT0"], ["IT0"], 0], "type": ["SUBJECT_PROCESS", "EVENT_CLOSE", "IPC_OBJECT_PIPE_UNNAMED"], "initlink": [36187, 0]}
{"link": [52405, 52405], "path": "null", "label": [["PT0"], ["PT0"], 0], "type": ["SUBJECT_PROCESS", "EVENT_EXECUTE", "SUBJECT_PROCESS"], "initlink": [36187, 36187]}
